{
  "kind": "collectionType",
  "collectionName": "blogs",
  "info": {
    "singularName": "blog",
    "pluralName": "blogs",
    "displayName": "blog"
  },
  "options": {
    "draftAndPublish": true
  },
  "pluginOptions": {},
  "attributes": {
    "title": {
      "type": "string"
    },
    "slug": {
      "type": "uid",
      "targetField": "title"
    },
    "excerpt": {
      "type": "text"
    },
    "content": {
      "type": "blocks"
    },
    "readTime": {
      "type": "biginteger"
    },
    "publishedOn": {
      "type": "datetime"
    },
    "tags": {
      "type": "json"
    },
    "coverImage": {
      "type": "media",
      "multiple": false,
      "allowedTypes": [
        "images",
        "files",
        "videos",
        "audios"
      ]
    }
  }
}
